{"type":"FeatureCollection","name":"ne_110m_geography_regions_points","crs":{"type":"name","properties":{"name":"urn:ogc:def:crs:OGC:1.3:CRS84"}},"features":[{"type":"Feature","properties":{"scalerank":2,"featurecla":"waterfall","name":"Niagara Falls","comment":null,"name_alt":null,"lat_y":43.087653,"long_x":-79.044073,"region":"North America","subregion":null,"min_zoom":5,"label":"Niagara Falls","name_ar":"شلالات نياجارا","name_bn":"নায়াগ্রা জলপ্রপাত","name_de":"Niagarafälle","name_en":"Niagara Falls","name_es":"Cataratas del Niágara","name_fr":"chutes du Niagara","name_el":"Καταρράκτες του Νιαγάρα","name_hi":"नायाग्रा जल प्रपात","name_hu":"Niagara-vízesés","name_id":"Niagara","name_it":"cascate del Niagara","name_ja":"ナイアガラの滝","name_ko":"나이아가라 폭포","name_nl":"Niagarawatervallen","name_pl":"Wodospad Niagara","name_pt":"Cataratas do Niágara","name_ru":"Ниагарский водопад","name_sv":"Niagarafallen","name_tr":"Niagara Şelalesi","name_vi":"Thác Niagara","name_zh":"尼亚加拉瀑布","wikidataid":"Q34221","wdid_score":3,"ne_id":1159105019},"bbox":[-79.044118,43.087714,-79.044118,43.087714],"geometry":{"type":"Point","coordinates":[-79.044118,43.087714]}},{"type":"Feature","properties":{"scalerank":2,"featurecla":"waterfall","name":"Salto Angel","comment":null,"name_alt":"Angel Falls","lat_y":5.686836,"long_x":-62.061848,"region":"South America","subregion":null,"min_zoom":5,"label":"Salto Angel","name_ar":"شلالات آنجل","name_bn":"অ্যাঞ্জেল জলপ্রপাত","name_de":"Salto Ángel","name_en":"Angel Falls","name_es":"Salto Ángel","name_fr":"Salto Angel","name_el":"Καταρράκτες Έιντζελ","name_hi":"एन्जिल जलप्रपात","name_hu":"Angel-vízesés","name_id":"Air terjun Angel","name_it":"Salto Angel","name_ja":"エンジェルフォール","name_ko":"앙헬 폭포","name_nl":"Ángelwaterval","name_pl":"Salto Angel","name_pt":"Salto Ángel","name_ru":"Анхель","name_sv":"Angelfallen","name_tr":"Angel Şelalesi","name_vi":"Thác nước Ángel","name_zh":"安赫尔瀑布","wikidataid":"Q80299","wdid_score":5,"ne_id":1159105051},"bbox":[-62.061818,5.686896,-62.061818,5.686896],"geometry":{"type":"Point","coordinates":[-62.061818,5.686896]}},{"type":"Feature","properties":{"scalerank":2,"featurecla":"waterfall","name":"Iguazu Falls","comment":null,"name_alt":null,"lat_y":-25.568265,"long_x":-54.582842,"region":"South America","subregion":null,"min_zoom":5,"label":"Iguazu Falls","name_ar":"شلالات إجوازو","name_bn":"ইগুয়াসু জলপ্রপাত","name_de":"Iguazú-Wasserfälle","name_en":"Iguaçu Falls","name_es":"Cataratas del Iguazú","name_fr":"chutes d'Iguazú","name_el":"Καταρράκτες Ιγκουασού","name_hi":null,"name_hu":"Iguazú-vízesés","name_id":"Air terjun Iguazu","name_it":"cascate dell'Iguazú","name_ja":"イグアスの滝","name_ko":"이구아수 폭포","name_nl":"Watervallen van de Iguaçu","name_pl":"Wodospad Iguazú","name_pt":"Cataratas do Iguaçu","name_ru":"Игуасу","name_sv":"Iguazúfallen","name_tr":"Iguazú Şelalesi","name_vi":"Thác Iguazu","name_zh":"伊瓜苏瀑布","wikidataid":"Q36332","wdid_score":5,"ne_id":1159105053},"bbox":[-54.582997,-25.568292,-54.582997,-25.568292],"geometry":{"type":"Point","coordinates":[-54.582997,-25.568292]}}],"bbox":[-79.0441178050725,-25.5682919250059,-54.5829971996038,43.0877139343691]}
