{
"type": "FeatureCollection",
                                                                                
"features": [
{ "type": "Feature", "properties": { "scalerank": 2, "featurecla": "waterfall", "name": "Niagara Falls", "comment": null, "name_alt": null, "lat_y": 43.087653, "long_x": -79.044073, "region": "North America", "subregion": null }, "geometry": { "type": "Point", "coordinates": [ -79.044117805072517, 43.087713934369077 ] } }
,
{ "type": "Feature", "properties": { "scalerank": 2, "featurecla": "waterfall", "name": "Salto Angel", "comment": null, "name_alt": "Angel Falls", "lat_y": 5.686836, "long_x": -62.061848, "region": "South America", "subregion": null }, "geometry": { "type": "Point", "coordinates": [ -62.061818000385017, 5.686896063275327 ] } }
,
{ "type": "Feature", "properties": { "scalerank": 2, "featurecla": "waterfall", "name": "Iguazu Falls", "comment": null, "name_alt": null, "lat_y": -25.568265, "long_x": -54.582842, "region": "South America", "subregion": null }, "geometry": { "type": "Point", "coordinates": [ -54.582997199603767, -25.568291925005923 ] } }

]
}
